gau_alpha/__init__.py
gau_alpha/layer.py
gau_alpha/modeling_gau_alpha.py
gau_alpha-0.0.3.dist-info/METADATA
gau_alpha-0.0.3.dist-info/WHEEL
gau_alpha-0.0.3.dist-info/top_level.txt
gau_alpha-0.0.3.dist-info/RECORD
